dagster_db/__init__.py
dagster_db/exceptions/failures.py
dagster_db/helpers/duckdb.py
dagster_db/helpers/generic_db.py
dagster_db/helpers/pandas.py
dagster_db/helpers/polars.py
dagster_db/helpers/sql_query.py
dagster_db/io_managers/custom_db_io_manager.py
dagster_db/io_managers/duckdb_io_manager.py
dagster_db/query/sql_query.py
dagster_db/type_handlers/custom_type_handler.py
dagster_db/type_handlers/duckdb_pandas.py
dagster_db/type_handlers/duckdb_polars.py
dagster_db/type_handlers/duckdb_sql_query.py
dagster_db-0.3.2.dist-info/METADATA
dagster_db-0.3.2.dist-info/WHEEL
dagster_db-0.3.2.dist-info/licenses/LICENSE
dagster_db-0.3.2.dist-info/RECORD
