Metadata-Version: 2.4
Name: dagster-db
Version: 0.3.2
Summary: Dagster IO managers and type handlers for databases
Project-URL: Source, https://github.com/j-blackwell/dagster-db
Author-email: James Blackwell <33688964+j-blackwell@users.noreply.github.com>
License: MIT License
License-File: LICENSE
Classifier: Development Status :: 3 - Alpha
Classifier: Programming Language :: Python :: 3.10
Classifier: Programming Language :: Python :: 3.11
Classifier: Programming Language :: Python :: 3.12
Classifier: Programming Language :: Python :: 3.13
Requires-Python: <3.14,>=3.10
Requires-Dist: dagster-pandas>=0.25.11
Requires-Dist: dagster-polars>=0.25.11
Requires-Dist: dagster>=1.9.11
Requires-Dist: jinja2>=3.1.5
Requires-Dist: sqlglot>=26.11.1
Provides-Extra: bigquery
Requires-Dist: dagster-gcp>=0.25.11; extra == 'bigquery'
Provides-Extra: duckdb
Requires-Dist: dagster-duckdb>=0.25.11; extra == 'duckdb'
